sym/cli/__init__.py
sym/cli/actions/__init__.py
sym/cli/actions/action_registry.py
sym/cli/actions/ansible_action.py
sym/cli/actions/ansible_playbook_action.py
sym/cli/actions/ssh_session_action.py
sym/cli/actions/sym_action.py
sym/cli/actions/write_creds_action.py
sym/cli/ansible/__init__.py
sym/cli/ansible/connection/__init__.py
sym/cli/ansible/connection/sym_aws_ssm.py
sym/cli/commands/__init__.py
sym/cli/commands/ansible.py
sym/cli/commands/ansible_playbook.py
sym/cli/commands/check.py
sym/cli/commands/config.py
sym/cli/commands/defaults.py
sym/cli/commands/doctor.py
sym/cli/commands/exec.py
sym/cli/commands/host_to_instance.py
sym/cli/commands/login.py
sym/cli/commands/resources.py
sym/cli/commands/ssh.py
sym/cli/commands/ssh_session.py
sym/cli/commands/ssh_tunnel.py
sym/cli/commands/ssm.py
sym/cli/commands/sym.py
sym/cli/commands/version.py
sym/cli/commands/write_creds.py
sym/cli/constants/__init__.py
sym/cli/constants/env.py
sym/cli/data/__init__.py
sym/cli/data/ansible_options.py
sym/cli/data/request_data.py
sym/cli/data/target_options.py
sym/cli/decorators.py
sym/cli/errors.py
sym/cli/helpers/__init__.py
sym/cli/helpers/ansible.py
sym/cli/helpers/boto.py
sym/cli/helpers/check/__init__.py
sym/cli/helpers/check/core.py
sym/cli/helpers/check/ec2.py
sym/cli/helpers/check/model.py
sym/cli/helpers/check/runner.py
sym/cli/helpers/check/ssh.py
sym/cli/helpers/config.py
sym/cli/helpers/constants.py
sym/cli/helpers/doctor.py
sym/cli/helpers/ec2/__init__.py
sym/cli/helpers/ec2/cache.py
sym/cli/helpers/ec2/client.py
sym/cli/helpers/ec2/factory.py
sym/cli/helpers/ec2/multiregion.py
sym/cli/helpers/flags.py
sym/cli/helpers/global_options.py
sym/cli/helpers/options.py
sym/cli/helpers/org.py
sym/cli/helpers/params.py
sym/cli/helpers/pty.py
sym/cli/helpers/ssh.py
sym/cli/helpers/sym_group.py
sym/cli/helpers/threading.py
sym/cli/helpers/validations.py
sym/cli/helpers/version.py
sym/cli/saml_clients/__init__.py
sym/cli/saml_clients/aws_config.py
sym_cli-0.6.1.dist-info/METADATA
sym_cli-0.6.1.dist-info/WHEEL
sym_cli-0.6.1.dist-info/entry_points.txt
sym_cli-0.6.1.dist-info/RECORD
