Metadata-Version: 2.1
Name: sym-cli
Version: 0.6.1
Summary: Sym's Official CLI for Users
Home-page: https://symops.com/
Author: SymOps, Inc.
Author-email: pypi@symops.io
Requires-Python: >=3.8,<4.0
Classifier: Operating System :: OS Independent
Classifier: Programming Language :: Python :: 3
Classifier: Programming Language :: Python :: 3.8
Classifier: Programming Language :: Python :: 3.9
Classifier: Programming Language :: Python :: 3.10
Classifier: Programming Language :: Python :: 3.11
Classifier: Programming Language :: Python :: 3
Requires-Dist: PyYAML (>=5.3.1,<6.0.0)
Requires-Dist: SecretStorage (>=3.2.0,<4.0.0)
Requires-Dist: analytics-python (>=1.3.1,<2.0.0)
Requires-Dist: boto3 (>=1.16.20,<2.0.0)
Requires-Dist: click (>=8.0.0,<9.0.0)
Requires-Dist: click-option-group (>=0.5.1,<0.6.0)
Requires-Dist: colorama (<0.4.4)
Requires-Dist: cryptography (==3.4.8)
Requires-Dist: immutables (>=0.14,<0.15)
Requires-Dist: keyring (>=21.5.0,<22.0.0)
Requires-Dist: mistune (<2.0.0)
Requires-Dist: policyuniverse (>=1.3.2,<2.0.0)
Requires-Dist: portalocker (>=2.0.0,<3.0.0)
Requires-Dist: python-dateutil (>=2.8.1,<3.0.0)
Requires-Dist: requests (>=2.25,<3.0)
Requires-Dist: semver (>=2.13.0,<3.0.0)
Requires-Dist: sentry-sdk (>=0.19.3,<0.20.0)
Requires-Dist: sym-shared-cli (>=0.2.3,<0.3.0)
Requires-Dist: urllib3 (==1.26.15)
Requires-Dist: validators (>=0.18.1,<0.19.0)
Project-URL: Documentation, https://docs.symops.com/docs/install-sym-cli
